LICENSE.md
MANIFEST.in
README.md
setup.py
hass_frontend/07d8aa21ae0160c22d94.chunk.js
hass_frontend/07d8aa21ae0160c22d94.chunk.js.LICENSE
hass_frontend/07d8aa21ae0160c22d94.chunk.js.gz
hass_frontend/07d8aa21ae0160c22d94.chunk.js.map
hass_frontend/0dffbec9c5ff7d8b5939.chunk.js
hass_frontend/0dffbec9c5ff7d8b5939.chunk.js.gz
hass_frontend/0dffbec9c5ff7d8b5939.chunk.js.map
hass_frontend/1d42a2792941bf19ce57.chunk.js
hass_frontend/1d42a2792941bf19ce57.chunk.js.LICENSE
hass_frontend/1d42a2792941bf19ce57.chunk.js.gz
hass_frontend/1d42a2792941bf19ce57.chunk.js.map
hass_frontend/1d4e397826daa99ffe91.chunk.js
hass_frontend/1d4e397826daa99ffe91.chunk.js.gz
hass_frontend/1d4e397826daa99ffe91.chunk.js.map
hass_frontend/2c8b4f22755ac855fc36.chunk.js
hass_frontend/2c8b4f22755ac855fc36.chunk.js.gz
hass_frontend/2c8b4f22755ac855fc36.chunk.js.map
hass_frontend/2d91a9dd7202cce77ad7.chunk.js
hass_frontend/2d91a9dd7202cce77ad7.chunk.js.gz
hass_frontend/2d91a9dd7202cce77ad7.chunk.js.map
hass_frontend/3449ae49bdaedc9696f3.chunk.js
hass_frontend/3449ae49bdaedc9696f3.chunk.js.LICENSE
hass_frontend/3449ae49bdaedc9696f3.chunk.js.gz
hass_frontend/3449ae49bdaedc9696f3.chunk.js.map
hass_frontend/3509e4aabf9a3c3ffd31.chunk.js
hass_frontend/3509e4aabf9a3c3ffd31.chunk.js.gz
hass_frontend/3509e4aabf9a3c3ffd31.chunk.js.map
hass_frontend/353a3d785a913a1fb4c1.chunk.js
hass_frontend/353a3d785a913a1fb4c1.chunk.js.gz
hass_frontend/353a3d785a913a1fb4c1.chunk.js.map
hass_frontend/3a65cc64a6398668efe1.chunk.js
hass_frontend/3a65cc64a6398668efe1.chunk.js.LICENSE
hass_frontend/3a65cc64a6398668efe1.chunk.js.gz
hass_frontend/3a65cc64a6398668efe1.chunk.js.map
hass_frontend/3ad73ce8310544768bde.chunk.js
hass_frontend/3ad73ce8310544768bde.chunk.js.LICENSE
hass_frontend/3ad73ce8310544768bde.chunk.js.gz
hass_frontend/3ad73ce8310544768bde.chunk.js.map
hass_frontend/3cb4f5f3ae8c8a3e5d55.chunk.js
hass_frontend/3cb4f5f3ae8c8a3e5d55.chunk.js.gz
hass_frontend/3cb4f5f3ae8c8a3e5d55.chunk.js.map
shimao_smart_frontend.egg-info/PKG-INFO
shimao_smart_frontend.egg-info/SOURCES.txt
shimao_smart_frontend.egg-info/dependency_links.txt
shimao_smart_frontend.egg-info/not-zip-safe
shimao_smart_frontend.egg-info/requires.txt
shimao_smart_frontend.egg-info/top_level.txt